flask_gun/__init__.py
flask_gun/api.py
flask_gun/constants.py
flask_gun/model_field.py
flask_gun/models.py
flask_gun/operation.py
flask_gun/param.py
flask_gun/param_functions.py
flask_gun/parse_rule.py
flask_gun/router.py
flask_gun/security.py
flask_gun/swagger-ui-5.9.1/favicon-16x16.png
flask_gun/swagger-ui-5.9.1/favicon-32x32.png
flask_gun/swagger-ui-5.9.1/index.j2
flask_gun/swagger-ui-5.9.1/README.md
flask_gun/swagger-ui-5.9.1/swagger-ui-bundle.js
flask_gun/swagger-ui-5.9.1/swagger-ui-standalone-preset.js
flask_gun/swagger-ui-5.9.1/swagger-ui.css
flask_gun/swagger_ui.py
flask_gun/utils.py
flask_gun-1.0.0.dist-info/METADATA
flask_gun-1.0.0.dist-info/WHEEL
flask_gun-1.0.0.dist-info/RECORD
