Metadata-Version: 2.1
Name: flask-gun
Version: 1.0.0
Summary: Flask Gun is a web framework for building APIs with Flask and Python 3.10+ type hints.
Author: Wumao
Author-email: 549240290@qq.com
Requires-Python: >=3.10,<4.0
Classifier: Programming Language :: Python :: 3
Classifier: Programming Language :: Python :: 3.10
Classifier: Programming Language :: Python :: 3.11
Classifier: Programming Language :: Python :: 3.12
Requires-Dist: Flask (>=2.3.0)
Requires-Dist: docstring-parser (>=0.14.1,<0.15.0)
Requires-Dist: pydantic (>=2.4.2,<3.0.0)
